MANIFEST.in
README.md
app.py
db.py
requirements.txt
setup.cfg
setup.py
air_connection_app.egg-info/PKG-INFO
air_connection_app.egg-info/SOURCES.txt
air_connection_app.egg-info/dependency_links.txt
air_connection_app.egg-info/requires.txt
air_connection_app.egg-info/top_level.txt