Metadata-Version: 2.1
Name: air-connection-app
Version: 0.1
Summary: air connection app
Home-page: http://gitlab-1914910442.us-west-2.elb.amazonaws.com/vverkholyak/python_app
Author: vverholyak
License: UNKNOWN
Platform: UNKNOWN
Classifier: License :: OSI Approved :: MIT License
Classifier: Operating System :: OS Independent
Classifier: Programming Language :: Python :: 3.6
Classifier: Programming Language :: Python :: 3.7
Classifier: Programming Language :: Python :: 3.8
Requires-Python: >=3.6
